currencyfield/__init__.py
currencyfield/fields.py
currencyfield/utils.py
django_currency_field-0.1.10.dist-info/LICENSE
django_currency_field-0.1.10.dist-info/METADATA
django_currency_field-0.1.10.dist-info/WHEEL
django_currency_field-0.1.10.dist-info/top_level.txt
django_currency_field-0.1.10.dist-info/RECORD
