Metadata-Version: 2.1
Name: django-currency-field
Version: 0.1.10
Summary: A Precision Bigint model field that avoids floats & decimals
Home-page: https://github.com/ab25db/django-currency-field
Author: Daniel Bernal
Author-email: d@contemporary.io
License: UNKNOWN
Keywords: django,currency,models,financial
Platform: UNKNOWN
Classifier: Programming Language :: Python :: 3
Classifier: License :: OSI Approved :: MIT License
Classifier: Operating System :: OS Independent
Requires-Python: >=3.6
Requires-Dist: Django (>=3.0.1)
Requires-Dist: djangorestframework (>=3.11.0)
